pytds/__init__.py
pytds/collate.py
pytds/connection.py
pytds/connection_pool.py
pytds/cursor.py
pytds/extensions.py
pytds/instance_browser_client.py
pytds/lcid.py
pytds/login.py
pytds/row_strategies.py
pytds/smp.py
pytds/sspi.py
pytds/tds.py
pytds/tds_base.py
pytds/tds_reader.py
pytds/tds_session.py
pytds/tds_socket.py
pytds/tds_types.py
pytds/tds_writer.py
pytds/tls.py
pytds/tz.py
pytds/utils.py
python_tds-1.16.0.dist-info/LICENSE.txt
python_tds-1.16.0.dist-info/METADATA
python_tds-1.16.0.dist-info/WHEEL
python_tds-1.16.0.dist-info/top_level.txt
python_tds-1.16.0.dist-info/zip-safe
python_tds-1.16.0.dist-info/RECORD
