Metadata-Version: 2.1
Name: python-tds
Version: 1.16.0
Summary: Python DBAPI driver for MSSQL using pure Python TDS (Tabular Data Stream) protocol implementation
Home-page: https://github.com/denisenkom/pytds
Author: Mikhail Denisenko
Author-email: denisenkom@gmail.com
License: MIT
Classifier: Development Status :: 4 - Beta
Classifier: Programming Language :: Python
Classifier: Programming Language :: Python :: 3.8
Classifier: Programming Language :: Python :: 3.9
Classifier: Programming Language :: Python :: 3.10
Classifier: Programming Language :: Python :: 3.11
Classifier: Programming Language :: Python :: 3.12
License-File: LICENSE.txt
